CHANGES.rst
LICENSE.txt
MANIFEST.in
README.rst
setup.py
js/__init__.py
js.bootstrap_wysihtml5.egg-info/PKG-INFO
js.bootstrap_wysihtml5.egg-info/SOURCES.txt
js.bootstrap_wysihtml5.egg-info/dependency_links.txt
js.bootstrap_wysihtml5.egg-info/entry_points.txt
js.bootstrap_wysihtml5.egg-info/namespace_packages.txt
js.bootstrap_wysihtml5.egg-info/not-zip-safe
js.bootstrap_wysihtml5.egg-info/requires.txt
js.bootstrap_wysihtml5.egg-info/top_level.txt
js/bootstrap_wysihtml5/__init__.py
js/bootstrap_wysihtml5/test_bootstrap_wysihtml5.rst
js/bootstrap_wysihtml5/resources/css/bootstrap-wysihtml5-0.0.2.css
js/bootstrap_wysihtml5/resources/js/bootstrap-wysihtml5-0.0.2.js
js/bootstrap_wysihtml5/resources/js/bootstrap-wysihtml5-0.0.2.min.js
js/bootstrap_wysihtml5/resources/js/bootstrap3-wysihtml5-0.0.2.js
js/bootstrap_wysihtml5/resources/js/bootstrap3-wysihtml5-0.0.2.min.js