Metadata-Version: 1.0
Name: js.bootstrap-wysihtml5
Version: 0.0.2.post3
Summary: Fanstatic packaging of bootstrap_wysihtml5
Home-page: https://github.com/teixas/js.bootstrap_wysihtml5
Author: Fanstatic Developers
Author-email: fanstatic@googlegroups.com
License: BSD
Platform: UNKNOWN
